LICENSE.txt
setup.py
code/__init__.py
ctkbox.egg-info/PKG-INFO
ctkbox.egg-info/SOURCES.txt
ctkbox.egg-info/dependency_links.txt
ctkbox.egg-info/top_level.txt