Metadata-Version: 2.1
Name: ctkbox
Version: 0.1
Summary: simple message box you can use it in CTK > ctkbox(msg)
Author: RedShadow
Classifier: Programming Language :: Python :: 3
Classifier: Operating System :: OS Independent
Classifier: License :: OSI Approved :: MIT License
License-File: LICENSE.txt
